[{"line":1,"column":1,"severity":"Warning","message":"Found more than One contract per file. 9 contracts found!","ruleId":"one-contract-per-file","fix":null,"filePath":"Benchmarks/Study_SamplesSet/7e833ddd83434ce7c79e6881f9933cce.sol"},{"line":1,"column":1,"severity":"Error","message":"Compiler version ^0.4.11 does not satisfy the ^0.8.0 semver requirement","ruleId":"compiler-version","fix":null,"filePath":"Benchmarks/Study_SamplesSet/7e833ddd83434ce7c79e6881f9933cce.sol"},{"line":41,"column":7,"severity":"Error","message":"Explicitly mark visibility in function","ruleId":"func-visibility","fix":null,"filePath":"Benchmarks/Study_SamplesSet/7e833ddd83434ce7c79e6881f9933cce.sol"},{"line":42,"column":7,"severity":"Error","message":"Explicitly mark visibility in function","ruleId":"func-visibility","fix":null,"filePath":"Benchmarks/Study_SamplesSet/7e833ddd83434ce7c79e6881f9933cce.sol"},{"line":51,"column":7,"severity":"Error","message":"Explicitly mark visibility in function","ruleId":"func-visibility","fix":null,"filePath":"Benchmarks/Study_SamplesSet/7e833ddd83434ce7c79e6881f9933cce.sol"},{"line":52,"column":7,"severity":"Error","message":"Explicitly mark visibility in function","ruleId":"func-visibility","fix":null,"filePath":"Benchmarks/Study_SamplesSet/7e833ddd83434ce7c79e6881f9933cce.sol"},{"line":53,"column":7,"severity":"Error","message":"Explicitly mark visibility in function","ruleId":"func-visibility","fix":null,"filePath":"Benchmarks/Study_SamplesSet/7e833ddd83434ce7c79e6881f9933cce.sol"},{"line":64,"column":7,"severity":"Error","message":"Explicitly mark visibility of state","ruleId":"state-visibility","fix":null,"filePath":"Benchmarks/Study_SamplesSet/7e833ddd83434ce7c79e6881f9933cce.sol"},{"line":71,"column":7,"severity":"Error","message":"Explicitly mark visibility in function","ruleId":"func-visibility","fix":null,"filePath":"Benchmarks/Study_SamplesSet/7e833ddd83434ce7c79e6881f9933cce.sol"},{"line":72,"column":9,"severity":"Warning","message":"Provide an error message for require","ruleId":"reason-string","fix":null,"filePath":"Benchmarks/Study_SamplesSet/7e833ddd83434ce7c79e6881f9933cce.sol"},{"line":72,"column":9,"severity":"Warning","message":"Use Custom Errors instead of require statements","ruleId":"custom-errors","fix":null,"filePath":"Benchmarks/Study_SamplesSet/7e833ddd83434ce7c79e6881f9933cce.sol"},{"line":77,"column":9,"severity":"Error","message":"Explicitly mark all external contracts as trusted or untrusted","ruleId":"mark-callable-contracts","filePath":"Benchmarks/Study_SamplesSet/7e833ddd83434ce7c79e6881f9933cce.sol"},{"line":86,"column":7,"severity":"Error","message":"Explicitly mark visibility in function","ruleId":"func-visibility","fix":null,"filePath":"Benchmarks/Study_SamplesSet/7e833ddd83434ce7c79e6881f9933cce.sol"},{"line":101,"column":7,"severity":"Error","message":"Explicitly mark visibility of state","ruleId":"state-visibility","fix":null,"filePath":"Benchmarks/Study_SamplesSet/7e833ddd83434ce7c79e6881f9933cce.sol"},{"line":110,"column":7,"severity":"Error","message":"Explicitly mark visibility in function","ruleId":"func-visibility","fix":null,"filePath":"Benchmarks/Study_SamplesSet/7e833ddd83434ce7c79e6881f9933cce.sol"},{"line":111,"column":9,"severity":"Warning","message":"Provide an error message for require","ruleId":"reason-string","fix":null,"filePath":"Benchmarks/Study_SamplesSet/7e833ddd83434ce7c79e6881f9933cce.sol"},{"line":111,"column":9,"severity":"Warning","message":"Use Custom Errors instead of require statements","ruleId":"custom-errors","fix":null,"filePath":"Benchmarks/Study_SamplesSet/7e833ddd83434ce7c79e6881f9933cce.sol"},{"line":121,"column":9,"severity":"Error","message":"Explicitly mark all external contracts as trusted or untrusted","ruleId":"mark-callable-contracts","filePath":"Benchmarks/Study_SamplesSet/7e833ddd83434ce7c79e6881f9933cce.sol"},{"line":130,"column":7,"severity":"Error","message":"Explicitly mark visibility in function","ruleId":"func-visibility","fix":null,"filePath":"Benchmarks/Study_SamplesSet/7e833ddd83434ce7c79e6881f9933cce.sol"},{"line":136,"column":9,"severity":"Warning","message":"Provide an error message for require","ruleId":"reason-string","fix":null,"filePath":"Benchmarks/Study_SamplesSet/7e833ddd83434ce7c79e6881f9933cce.sol"},{"line":136,"column":9,"severity":"Warning","message":"Use Custom Errors instead of require statements","ruleId":"custom-errors","fix":null,"filePath":"Benchmarks/Study_SamplesSet/7e833ddd83434ce7c79e6881f9933cce.sol"},{"line":139,"column":9,"severity":"Error","message":"Explicitly mark all external contracts as trusted or untrusted","ruleId":"mark-callable-contracts","filePath":"Benchmarks/Study_SamplesSet/7e833ddd83434ce7c79e6881f9933cce.sol"},{"line":149,"column":7,"severity":"Error","message":"Explicitly mark visibility in function","ruleId":"func-visibility","fix":null,"filePath":"Benchmarks/Study_SamplesSet/7e833ddd83434ce7c79e6881f9933cce.sol"},{"line":159,"column":7,"severity":"Error","message":"Explicitly mark visibility in function","ruleId":"func-visibility","fix":null,"filePath":"Benchmarks/Study_SamplesSet/7e833ddd83434ce7c79e6881f9933cce.sol"},{"line":159,"column":52,"severity":"Warning","message":"Rule is set with explicit type [var/s: uint]","ruleId":"explicit-types","filePath":"Benchmarks/Study_SamplesSet/7e833ddd83434ce7c79e6881f9933cce.sol"},{"line":162,"column":9,"severity":"Error","message":"Explicitly mark all external contracts as trusted or untrusted","ruleId":"mark-callable-contracts","filePath":"Benchmarks/Study_SamplesSet/7e833ddd83434ce7c79e6881f9933cce.sol"},{"line":166,"column":7,"severity":"Error","message":"Explicitly mark visibility in function","ruleId":"func-visibility","fix":null,"filePath":"Benchmarks/Study_SamplesSet/7e833ddd83434ce7c79e6881f9933cce.sol"},{"line":166,"column":52,"severity":"Warning","message":"Rule is set with explicit type [var/s: uint]","ruleId":"explicit-types","filePath":"Benchmarks/Study_SamplesSet/7e833ddd83434ce7c79e6881f9933cce.sol"},{"line":168,"column":9,"severity":"Warning","message":"Rule is set with explicit type [var/s: uint]","ruleId":"explicit-types","filePath":"Benchmarks/Study_SamplesSet/7e833ddd83434ce7c79e6881f9933cce.sol"},{"line":174,"column":9,"severity":"Error","message":"Explicitly mark all external contracts as trusted or untrusted","ruleId":"mark-callable-contracts","filePath":"Benchmarks/Study_SamplesSet/7e833ddd83434ce7c79e6881f9933cce.sol"},{"line":196,"column":7,"severity":"Error","message":"Explicitly mark visibility in function (Set ignoreConstructors to true if using solidity >=0.7.0)","ruleId":"func-visibility","fix":null,"filePath":"Benchmarks/Study_SamplesSet/7e833ddd83434ce7c79e6881f9933cce.sol"},{"line":205,"column":9,"severity":"Warning","message":"Provide an error message for require","ruleId":"reason-string","fix":null,"filePath":"Benchmarks/Study_SamplesSet/7e833ddd83434ce7c79e6881f9933cce.sol"},{"line":205,"column":9,"severity":"Warning","message":"Use Custom Errors instead of require statements","ruleId":"custom-errors","fix":null,"filePath":"Benchmarks/Study_SamplesSet/7e833ddd83434ce7c79e6881f9933cce.sol"},{"line":214,"column":7,"severity":"Error","message":"Explicitly mark visibility in function","ruleId":"func-visibility","fix":null,"filePath":"Benchmarks/Study_SamplesSet/7e833ddd83434ce7c79e6881f9933cce.sol"},{"line":215,"column":9,"severity":"Warning","message":"Provide an error message for require","ruleId":"reason-string","fix":null,"filePath":"Benchmarks/Study_SamplesSet/7e833ddd83434ce7c79e6881f9933cce.sol"},{"line":215,"column":9,"severity":"Warning","message":"Use Custom Errors instead of require statements","ruleId":"custom-errors","fix":null,"filePath":"Benchmarks/Study_SamplesSet/7e833ddd83434ce7c79e6881f9933cce.sol"},{"line":216,"column":9,"severity":"Error","message":"Explicitly mark all external contracts as trusted or untrusted","ruleId":"mark-callable-contracts","filePath":"Benchmarks/Study_SamplesSet/7e833ddd83434ce7c79e6881f9933cce.sol"},{"line":226,"column":5,"severity":"Warning","message":"Rule is set with explicit type [var/s: uint]","ruleId":"explicit-types","filePath":"Benchmarks/Study_SamplesSet/7e833ddd83434ce7c79e6881f9933cce.sol"},{"line":226,"column":5,"severity":"Warning","message":"Variable name must be in mixedCase","ruleId":"var-name-mixedcase","fix":null,"filePath":"Benchmarks/Study_SamplesSet/7e833ddd83434ce7c79e6881f9933cce.sol"},{"line":227,"column":5,"severity":"Warning","message":"Rule is set with explicit type [var/s: uint]","ruleId":"explicit-types","filePath":"Benchmarks/Study_SamplesSet/7e833ddd83434ce7c79e6881f9933cce.sol"},{"line":227,"column":5,"severity":"Warning","message":"Variable name must be in mixedCase","ruleId":"var-name-mixedcase","fix":null,"filePath":"Benchmarks/Study_SamplesSet/7e833ddd83434ce7c79e6881f9933cce.sol"},{"line":231,"column":5,"severity":"Error","message":"Explicitly mark visibility in function","ruleId":"func-visibility","fix":null,"filePath":"Benchmarks/Study_SamplesSet/7e833ddd83434ce7c79e6881f9933cce.sol"},{"line":232,"column":9,"severity":"Warning","message":"Provide an error message for require","ruleId":"reason-string","fix":null,"filePath":"Benchmarks/Study_SamplesSet/7e833ddd83434ce7c79e6881f9933cce.sol"},{"line":232,"column":9,"severity":"Warning","message":"Use Custom Errors instead of require statements","ruleId":"custom-errors","fix":null,"filePath":"Benchmarks/Study_SamplesSet/7e833ddd83434ce7c79e6881f9933cce.sol"},{"line":233,"column":9,"severity":"Warning","message":"Provide an error message for require","ruleId":"reason-string","fix":null,"filePath":"Benchmarks/Study_SamplesSet/7e833ddd83434ce7c79e6881f9933cce.sol"},{"line":233,"column":9,"severity":"Warning","message":"Use Custom Errors instead of require statements","ruleId":"custom-errors","fix":null,"filePath":"Benchmarks/Study_SamplesSet/7e833ddd83434ce7c79e6881f9933cce.sol"},{"line":235,"column":24,"severity":"Error","message":"Avoid making time-based decisions in your business logic","ruleId":"not-rely-on-time","fix":null,"filePath":"Benchmarks/Study_SamplesSet/7e833ddd83434ce7c79e6881f9933cce.sol"},{"line":240,"column":9,"severity":"Warning","message":"Provide an error message for require","ruleId":"reason-string","fix":null,"filePath":"Benchmarks/Study_SamplesSet/7e833ddd83434ce7c79e6881f9933cce.sol"},{"line":240,"column":9,"severity":"Warning","message":"Use Custom Errors instead of require statements","ruleId":"custom-errors","fix":null,"filePath":"Benchmarks/Study_SamplesSet/7e833ddd83434ce7c79e6881f9933cce.sol"},{"line":241,"column":9,"severity":"Warning","message":"Provide an error message for require","ruleId":"reason-string","fix":null,"filePath":"Benchmarks/Study_SamplesSet/7e833ddd83434ce7c79e6881f9933cce.sol"},{"line":241,"column":9,"severity":"Warning","message":"Use Custom Errors instead of require statements","ruleId":"custom-errors","fix":null,"filePath":"Benchmarks/Study_SamplesSet/7e833ddd83434ce7c79e6881f9933cce.sol"},{"line":244,"column":4,"severity":"Warning","message":"Rule is set with explicit type [var/s: uint]","ruleId":"explicit-types","filePath":"Benchmarks/Study_SamplesSet/7e833ddd83434ce7c79e6881f9933cce.sol"},{"line":246,"column":4,"severity":"Warning","message":"Provide an error message for require","ruleId":"reason-string","fix":null,"filePath":"Benchmarks/Study_SamplesSet/7e833ddd83434ce7c79e6881f9933cce.sol"},{"line":246,"column":4,"severity":"Warning","message":"Use Custom Errors instead of require statements","ruleId":"custom-errors","fix":null,"filePath":"Benchmarks/Study_SamplesSet/7e833ddd83434ce7c79e6881f9933cce.sol"},{"line":248,"column":4,"severity":"Error","message":"Explicitly mark all external contracts as trusted or untrusted","ruleId":"mark-callable-contracts","filePath":"Benchmarks/Study_SamplesSet/7e833ddd83434ce7c79e6881f9933cce.sol"},{"line":251,"column":9,"severity":"Error","message":"Possible reentrancy vulnerabilities. Avoid state changes after transfer.","ruleId":"reentrancy","fix":null,"filePath":"Benchmarks/Study_SamplesSet/7e833ddd83434ce7c79e6881f9933cce.sol"},{"line":256,"column":5,"severity":"Error","message":"Explicitly mark visibility in function","ruleId":"func-visibility","fix":null,"filePath":"Benchmarks/Study_SamplesSet/7e833ddd83434ce7c79e6881f9933cce.sol"},{"line":260,"column":5,"severity":"Error","message":"Explicitly mark visibility in function","ruleId":"func-visibility","fix":null,"filePath":"Benchmarks/Study_SamplesSet/7e833ddd83434ce7c79e6881f9933cce.sol"},{"line":262,"column":43,"severity":"Warning","message":"Provide an error message for require","ruleId":"reason-string","fix":null,"filePath":"Benchmarks/Study_SamplesSet/7e833ddd83434ce7c79e6881f9933cce.sol"},{"line":262,"column":43,"severity":"Warning","message":"Use Custom Errors instead of require statements","ruleId":"custom-errors","fix":null,"filePath":"Benchmarks/Study_SamplesSet/7e833ddd83434ce7c79e6881f9933cce.sol"},{"line":263,"column":36,"severity":"Warning","message":"Provide an error message for require","ruleId":"reason-string","fix":null,"filePath":"Benchmarks/Study_SamplesSet/7e833ddd83434ce7c79e6881f9933cce.sol"},{"line":263,"column":36,"severity":"Warning","message":"Use Custom Errors instead of require statements","ruleId":"custom-errors","fix":null,"filePath":"Benchmarks/Study_SamplesSet/7e833ddd83434ce7c79e6881f9933cce.sol"},{"line":269,"column":2,"severity":"Error","message":"Explicitly mark visibility in function","ruleId":"func-visibility","fix":null,"filePath":"Benchmarks/Study_SamplesSet/7e833ddd83434ce7c79e6881f9933cce.sol"},{"line":271,"column":38,"severity":"Warning","message":"Provide an error message for require","ruleId":"reason-string","fix":null,"filePath":"Benchmarks/Study_SamplesSet/7e833ddd83434ce7c79e6881f9933cce.sol"},{"line":271,"column":38,"severity":"Warning","message":"Use Custom Errors instead of require statements","ruleId":"custom-errors","fix":null,"filePath":"Benchmarks/Study_SamplesSet/7e833ddd83434ce7c79e6881f9933cce.sol"},{"line":272,"column":36,"severity":"Warning","message":"Provide an error message for require","ruleId":"reason-string","fix":null,"filePath":"Benchmarks/Study_SamplesSet/7e833ddd83434ce7c79e6881f9933cce.sol"},{"line":272,"column":36,"severity":"Warning","message":"Use Custom Errors instead of require statements","ruleId":"custom-errors","fix":null,"filePath":"Benchmarks/Study_SamplesSet/7e833ddd83434ce7c79e6881f9933cce.sol"},{"line":288,"column":5,"severity":"Warning","message":"Rule is set with explicit type [var/s: uint]","ruleId":"explicit-types","filePath":"Benchmarks/Study_SamplesSet/7e833ddd83434ce7c79e6881f9933cce.sol"},{"line":294,"column":60,"severity":"Warning","message":"Visibility modifier must be first in list of modifiers","ruleId":"visibility-modifier-order","fix":null,"filePath":"Benchmarks/Study_SamplesSet/7e833ddd83434ce7c79e6881f9933cce.sol"},{"line":298,"column":9,"severity":"Error","message":"Explicitly mark all external contracts as trusted or untrusted","ruleId":"mark-callable-contracts","filePath":"Benchmarks/Study_SamplesSet/7e833ddd83434ce7c79e6881f9933cce.sol"},{"line":299,"column":9,"severity":"Error","message":"Explicitly mark all external contracts as trusted or untrusted","ruleId":"mark-callable-contracts","filePath":"Benchmarks/Study_SamplesSet/7e833ddd83434ce7c79e6881f9933cce.sol"},{"line":304,"column":5,"severity":"Error","message":"Explicitly mark visibility in function","ruleId":"func-visibility","fix":null,"filePath":"Benchmarks/Study_SamplesSet/7e833ddd83434ce7c79e6881f9933cce.sol"},{"line":305,"column":9,"severity":"Warning","message":"Provide an error message for require","ruleId":"reason-string","fix":null,"filePath":"Benchmarks/Study_SamplesSet/7e833ddd83434ce7c79e6881f9933cce.sol"},{"line":305,"column":9,"severity":"Warning","message":"Use Custom Errors instead of require statements","ruleId":"custom-errors","fix":null,"filePath":"Benchmarks/Study_SamplesSet/7e833ddd83434ce7c79e6881f9933cce.sol"},{"line":309,"column":5,"severity":"Error","message":"Explicitly mark visibility in function","ruleId":"func-visibility","fix":null,"filePath":"Benchmarks/Study_SamplesSet/7e833ddd83434ce7c79e6881f9933cce.sol"},{"line":313,"column":9,"severity":"Error","message":"Explicitly mark all external contracts as trusted or untrusted","ruleId":"mark-callable-contracts","filePath":"Benchmarks/Study_SamplesSet/7e833ddd83434ce7c79e6881f9933cce.sol"},{"line":318,"column":5,"severity":"Error","message":"Explicitly mark visibility in function","ruleId":"func-visibility","fix":null,"filePath":"Benchmarks/Study_SamplesSet/7e833ddd83434ce7c79e6881f9933cce.sol"},{"line":319,"column":9,"severity":"Warning","message":"Provide an error message for require","ruleId":"reason-string","fix":null,"filePath":"Benchmarks/Study_SamplesSet/7e833ddd83434ce7c79e6881f9933cce.sol"},{"line":319,"column":9,"severity":"Warning","message":"Use Custom Errors instead of require statements","ruleId":"custom-errors","fix":null,"filePath":"Benchmarks/Study_SamplesSet/7e833ddd83434ce7c79e6881f9933cce.sol"},{"line":320,"column":9,"severity":"Warning","message":"Provide an error message for require","ruleId":"reason-string","fix":null,"filePath":"Benchmarks/Study_SamplesSet/7e833ddd83434ce7c79e6881f9933cce.sol"},{"line":320,"column":9,"severity":"Warning","message":"Use Custom Errors instead of require statements","ruleId":"custom-errors","fix":null,"filePath":"Benchmarks/Study_SamplesSet/7e833ddd83434ce7c79e6881f9933cce.sol"},{"line":320,"column":17,"severity":"Error","message":"Avoid making time-based decisions in your business logic","ruleId":"not-rely-on-time","fix":null,"filePath":"Benchmarks/Study_SamplesSet/7e833ddd83434ce7c79e6881f9933cce.sol"},{"line":324,"column":9,"severity":"Warning","message":"Provide an error message for require","ruleId":"reason-string","fix":null,"filePath":"Benchmarks/Study_SamplesSet/7e833ddd83434ce7c79e6881f9933cce.sol"},{"line":324,"column":9,"severity":"Warning","message":"Use Custom Errors instead of require statements","ruleId":"custom-errors","fix":null,"filePath":"Benchmarks/Study_SamplesSet/7e833ddd83434ce7c79e6881f9933cce.sol"},{"line":326,"column":9,"severity":"Error","message":"Explicitly mark all external contracts as trusted or untrusted","ruleId":"mark-callable-contracts","filePath":"Benchmarks/Study_SamplesSet/7e833ddd83434ce7c79e6881f9933cce.sol"},{"line":336,"column":5,"severity":"Warning","message":"Rule is set with explicit type [var/s: uint]","ruleId":"explicit-types","filePath":"Benchmarks/Study_SamplesSet/7e833ddd83434ce7c79e6881f9933cce.sol"},{"line":338,"column":5,"severity":"Warning","message":"Rule is set with explicit type [var/s: uint]","ruleId":"explicit-types","filePath":"Benchmarks/Study_SamplesSet/7e833ddd83434ce7c79e6881f9933cce.sol"},{"line":339,"column":5,"severity":"Warning","message":"Rule is set with explicit type [var/s: uint]","ruleId":"explicit-types","filePath":"Benchmarks/Study_SamplesSet/7e833ddd83434ce7c79e6881f9933cce.sol"},{"line":340,"column":5,"severity":"Warning","message":"Rule is set with explicit type [var/s: uint]","ruleId":"explicit-types","filePath":"Benchmarks/Study_SamplesSet/7e833ddd83434ce7c79e6881f9933cce.sol"},{"line":340,"column":5,"severity":"Warning","message":"Variable name must be in mixedCase","ruleId":"var-name-mixedcase","fix":null,"filePath":"Benchmarks/Study_SamplesSet/7e833ddd83434ce7c79e6881f9933cce.sol"},{"line":341,"column":5,"severity":"Warning","message":"Rule is set with explicit type [var/s: uint]","ruleId":"explicit-types","filePath":"Benchmarks/Study_SamplesSet/7e833ddd83434ce7c79e6881f9933cce.sol"},{"line":341,"column":5,"severity":"Warning","message":"Variable name must be in mixedCase","ruleId":"var-name-mixedcase","fix":null,"filePath":"Benchmarks/Study_SamplesSet/7e833ddd83434ce7c79e6881f9933cce.sol"},{"line":346,"column":5,"severity":"Error","message":"Explicitly mark visibility in function (Set ignoreConstructors to true if using solidity >=0.7.0)","ruleId":"func-visibility","fix":null,"filePath":"Benchmarks/Study_SamplesSet/7e833ddd83434ce7c79e6881f9933cce.sol"},{"line":350,"column":5,"severity":"Error","message":"Explicitly mark visibility in function","ruleId":"func-visibility","fix":null,"filePath":"Benchmarks/Study_SamplesSet/7e833ddd83434ce7c79e6881f9933cce.sol"},{"line":354,"column":5,"severity":"Error","message":"Explicitly mark visibility in function","ruleId":"func-visibility","fix":null,"filePath":"Benchmarks/Study_SamplesSet/7e833ddd83434ce7c79e6881f9933cce.sol"},{"line":355,"column":17,"severity":"Error","message":"Avoid making time-based decisions in your business logic","ruleId":"not-rely-on-time","fix":null,"filePath":"Benchmarks/Study_SamplesSet/7e833ddd83434ce7c79e6881f9933cce.sol"},{"line":355,"column":42,"severity":"Error","message":"Avoid making time-based decisions in your business logic","ruleId":"not-rely-on-time","fix":null,"filePath":"Benchmarks/Study_SamplesSet/7e833ddd83434ce7c79e6881f9933cce.sol"},{"line":355,"column":67,"severity":"Error","message":"Avoid making time-based decisions in your business logic","ruleId":"not-rely-on-time","fix":null,"filePath":"Benchmarks/Study_SamplesSet/7e833ddd83434ce7c79e6881f9933cce.sol"},{"line":355,"column":73,"severity":"Error","message":"Explicitly mark all external contracts as trusted or untrusted","ruleId":"mark-callable-contracts","filePath":"Benchmarks/Study_SamplesSet/7e833ddd83434ce7c79e6881f9933cce.sol"},{"line":355,"column":89,"severity":"Error","message":"Avoid making time-based decisions in your business logic","ruleId":"not-rely-on-time","fix":null,"filePath":"Benchmarks/Study_SamplesSet/7e833ddd83434ce7c79e6881f9933cce.sol"},{"line":355,"column":95,"severity":"Error","message":"Explicitly mark all external contracts as trusted or untrusted","ruleId":"mark-callable-contracts","filePath":"Benchmarks/Study_SamplesSet/7e833ddd83434ce7c79e6881f9933cce.sol"},{"line":356,"column":9,"severity":"Warning","message":"Provide an error message for require","ruleId":"reason-string","fix":null,"filePath":"Benchmarks/Study_SamplesSet/7e833ddd83434ce7c79e6881f9933cce.sol"},{"line":356,"column":9,"severity":"Warning","message":"Use Custom Errors instead of require statements","ruleId":"custom-errors","fix":null,"filePath":"Benchmarks/Study_SamplesSet/7e833ddd83434ce7c79e6881f9933cce.sol"},{"line":357,"column":9,"severity":"Warning","message":"Provide an error message for require","ruleId":"reason-string","fix":null,"filePath":"Benchmarks/Study_SamplesSet/7e833ddd83434ce7c79e6881f9933cce.sol"},{"line":357,"column":9,"severity":"Warning","message":"Use Custom Errors instead of require statements","ruleId":"custom-errors","fix":null,"filePath":"Benchmarks/Study_SamplesSet/7e833ddd83434ce7c79e6881f9933cce.sol"},{"line":359,"column":9,"severity":"Warning","message":"Rule is set with explicit type [var/s: uint]","ruleId":"explicit-types","filePath":"Benchmarks/Study_SamplesSet/7e833ddd83434ce7c79e6881f9933cce.sol"},{"line":359,"column":36,"severity":"Error","message":"Avoid making time-based decisions in your business logic","ruleId":"not-rely-on-time","fix":null,"filePath":"Benchmarks/Study_SamplesSet/7e833ddd83434ce7c79e6881f9933cce.sol"},{"line":361,"column":9,"severity":"Warning","message":"Provide an error message for require","ruleId":"reason-string","fix":null,"filePath":"Benchmarks/Study_SamplesSet/7e833ddd83434ce7c79e6881f9933cce.sol"},{"line":361,"column":9,"severity":"Warning","message":"Use Custom Errors instead of require statements","ruleId":"custom-errors","fix":null,"filePath":"Benchmarks/Study_SamplesSet/7e833ddd83434ce7c79e6881f9933cce.sol"},{"line":362,"column":9,"severity":"Warning","message":"Provide an error message for require","ruleId":"reason-string","fix":null,"filePath":"Benchmarks/Study_SamplesSet/7e833ddd83434ce7c79e6881f9933cce.sol"},{"line":362,"column":9,"severity":"Warning","message":"Use Custom Errors instead of require statements","ruleId":"custom-errors","fix":null,"filePath":"Benchmarks/Study_SamplesSet/7e833ddd83434ce7c79e6881f9933cce.sol"},{"line":364,"column":9,"severity":"Error","message":"Possible reentrancy vulnerabilities. Avoid state changes after transfer.","ruleId":"reentrancy","fix":null,"filePath":"Benchmarks/Study_SamplesSet/7e833ddd83434ce7c79e6881f9933cce.sol"},{"line":366,"column":9,"severity":"Error","message":"Explicitly mark all external contracts as trusted or untrusted","ruleId":"mark-callable-contracts","filePath":"Benchmarks/Study_SamplesSet/7e833ddd83434ce7c79e6881f9933cce.sol"},{"line":369,"column":5,"severity":"Error","message":"Explicitly mark visibility in function","ruleId":"func-visibility","fix":null,"filePath":"Benchmarks/Study_SamplesSet/7e833ddd83434ce7c79e6881f9933cce.sol"},{"line":370,"column":9,"severity":"Warning","message":"Provide an error message for require","ruleId":"reason-string","fix":null,"filePath":"Benchmarks/Study_SamplesSet/7e833ddd83434ce7c79e6881f9933cce.sol"},{"line":370,"column":9,"severity":"Warning","message":"Use Custom Errors instead of require statements","ruleId":"custom-errors","fix":null,"filePath":"Benchmarks/Study_SamplesSet/7e833ddd83434ce7c79e6881f9933cce.sol"},{"line":371,"column":9,"severity":"Warning","message":"Provide an error message for require","ruleId":"reason-string","fix":null,"filePath":"Benchmarks/Study_SamplesSet/7e833ddd83434ce7c79e6881f9933cce.sol"},{"line":371,"column":9,"severity":"Warning","message":"Use Custom Errors instead of require statements","ruleId":"custom-errors","fix":null,"filePath":"Benchmarks/Study_SamplesSet/7e833ddd83434ce7c79e6881f9933cce.sol"},{"line":374,"column":9,"severity":"Error","message":"Possible reentrancy vulnerabilities. Avoid state changes after transfer.","ruleId":"reentrancy","fix":null,"filePath":"Benchmarks/Study_SamplesSet/7e833ddd83434ce7c79e6881f9933cce.sol"},{"conclusion":"119 problem/s (52 error/s, 67 warning/s)"}]
