[{"line":1,"column":1,"severity":"Warning","message":"Found more than One contract per file. 2 contracts found!","ruleId":"one-contract-per-file","fix":null,"filePath":"Benchmarks/Study_SamplesSet/eebbd1de0bd005402b5dde75513c45f6.sol"},{"line":1,"column":1,"severity":"Error","message":"Compiler version ^0.4.0 does not satisfy the ^0.8.0 semver requirement","ruleId":"compiler-version","fix":null,"filePath":"Benchmarks/Study_SamplesSet/eebbd1de0bd005402b5dde75513c45f6.sol"},{"line":4,"column":5,"severity":"Error","message":"Explicitly mark visibility in function","ruleId":"func-visibility","fix":null,"filePath":"Benchmarks/Study_SamplesSet/eebbd1de0bd005402b5dde75513c45f6.sol"},{"line":5,"column":5,"severity":"Error","message":"Explicitly mark visibility in function","ruleId":"func-visibility","fix":null,"filePath":"Benchmarks/Study_SamplesSet/eebbd1de0bd005402b5dde75513c45f6.sol"},{"line":6,"column":5,"severity":"Error","message":"Explicitly mark visibility in function","ruleId":"func-visibility","fix":null,"filePath":"Benchmarks/Study_SamplesSet/eebbd1de0bd005402b5dde75513c45f6.sol"},{"line":7,"column":5,"severity":"Error","message":"Explicitly mark visibility in function","ruleId":"func-visibility","fix":null,"filePath":"Benchmarks/Study_SamplesSet/eebbd1de0bd005402b5dde75513c45f6.sol"},{"line":8,"column":5,"severity":"Error","message":"Explicitly mark visibility in function","ruleId":"func-visibility","fix":null,"filePath":"Benchmarks/Study_SamplesSet/eebbd1de0bd005402b5dde75513c45f6.sol"},{"line":9,"column":5,"severity":"Error","message":"Explicitly mark visibility in function","ruleId":"func-visibility","fix":null,"filePath":"Benchmarks/Study_SamplesSet/eebbd1de0bd005402b5dde75513c45f6.sol"},{"line":10,"column":5,"severity":"Error","message":"Explicitly mark visibility in function","ruleId":"func-visibility","fix":null,"filePath":"Benchmarks/Study_SamplesSet/eebbd1de0bd005402b5dde75513c45f6.sol"},{"line":27,"column":5,"severity":"Error","message":"Explicitly mark visibility in function (Set ignoreConstructors to true if using solidity >=0.7.0)","ruleId":"func-visibility","fix":null,"filePath":"Benchmarks/Study_SamplesSet/eebbd1de0bd005402b5dde75513c45f6.sol"},{"line":28,"column":15,"severity":"Error","message":"Explicitly mark all external contracts as trusted or untrusted","ruleId":"mark-callable-contracts","filePath":"Benchmarks/Study_SamplesSet/eebbd1de0bd005402b5dde75513c45f6.sol"},{"line":38,"column":5,"severity":"Error","message":"Explicitly mark visibility in function","ruleId":"func-visibility","fix":null,"filePath":"Benchmarks/Study_SamplesSet/eebbd1de0bd005402b5dde75513c45f6.sol"},{"line":41,"column":16,"severity":"Error","message":"Use \"keccak256\" instead of deprecated \"sha3\"","ruleId":"avoid-sha3","filePath":"Benchmarks/Study_SamplesSet/eebbd1de0bd005402b5dde75513c45f6.sol"},{"line":49,"column":5,"severity":"Error","message":"Explicitly mark visibility in function","ruleId":"func-visibility","fix":null,"filePath":"Benchmarks/Study_SamplesSet/eebbd1de0bd005402b5dde75513c45f6.sol"},{"line":50,"column":16,"severity":"Error","message":"Use \"keccak256\" instead of deprecated \"sha3\"","ruleId":"avoid-sha3","filePath":"Benchmarks/Study_SamplesSet/eebbd1de0bd005402b5dde75513c45f6.sol"},{"line":61,"column":9,"severity":"Error","message":"Avoid to use inline assembly. It is acceptable only in rare cases","ruleId":"no-inline-assembly","fix":null,"filePath":"Benchmarks/Study_SamplesSet/eebbd1de0bd005402b5dde75513c45f6.sol"},{"conclusion":"16 problem/s (15 error/s, 1 warning/s)"}]
